musegan/__init__.py
musegan/_version.py
musegan/archs/__init__.py
musegan/archs/bar_generator.py
musegan/archs/critic.py
musegan/archs/generator.py
musegan/archs/temp_network.py
musegan/archs/utils.py
musegan/dataset/__init__.py
musegan/dataset/data_utils.py
musegan/trainner/__init__.py
musegan/trainner/criterion.py
musegan/trainner/trainer.py
musegan-0.1.5.dist-info/LICENSE
musegan-0.1.5.dist-info/METADATA
musegan-0.1.5.dist-info/WHEEL
musegan-0.1.5.dist-info/top_level.txt
musegan-0.1.5.dist-info/RECORD
