Metadata-Version: 2.1
Name: musegan
Version: 0.1.5
Summary: A pytorch implementation of musegan
Home-page: https://github.com/cliffordkleinsr/musegan-pytorch
Author: Clifford Njoroge
Author-email: cnjoroge@gmail.com
Classifier: Programming Language :: Python :: 3
Classifier: Programming Language :: Python :: 3.7
Classifier: Programming Language :: Python :: 3.8
Classifier: Programming Language :: Python :: 3.9
Classifier: Programming Language :: Python :: 3.10
Classifier: License :: OSI Approved :: MIT License
Classifier: Operating System :: OS Independent
Requires-Python: >=3.10
License-File: LICENSE
Requires-Dist: music21
Requires-Dist: numpy (>=1.24.3)
